<?xml version="1.0" encoding="utf-8" standalone="yes"?>
<channel>
	<id>filmpertutti</id>
	<name>Filmpertutti</name>

	<active>true</active>
	<adult>false</adult>
	<language>it</language>

	<fanart>https://raw.githubusercontent.com/stesev1/channels/master/images/background/background.jpg</fanart>
	<thumbnail>https://raw.githubusercontent.com/stesev1/channels/master/images/filmpertutti.png</thumbnail>
	<thumbnail>https://raw.githubusercontent.com/stesev1/channels/master/images/filmpertutti.png</thumbnail>

	<update_url>https://raw.githubusercontent.com/stesev1/channels/master/channels/</update_url>
	<version>18</version>
	<date>31/12/2018</date>
	<changes>Update</changes>

	<categories>
		<category>movie</category>
		<category>serie</category>
		<category>top channels</category>
	</categories>

	<settings>
		<id>include_in_global_search</id>
		<type>bool</type>
		<label>Includi ricerca globale</label>
		<default>true</default>
		<enabled>true</enabled>
		<visible>true</visible>
	</settings>

	<settings>
		<id>include_in_newest_peliculas</id>
		<type>bool</type>
		<label>Includi in novità - film</label>
		<default>true</default>
		<enabled>true</enabled>
		<visible>true</visible>
	</settings>
</channel>
