<item>
	<title>[COLOR=white]The Richest Man In Walnut Grove[/COLOR]</title>
	<meta>
	<imdb>tt0071007</imdb>
	<content>episode</content>
	<tvshowtitle>Little House on the Prairie</tvshowtitle>
	<year>1975</year>
	<season>2</season>
	<episode>1</episode>
	</meta>
	<link>
	<sublink>search</sublink>
	<sublink>searchsd</sublink>
	</link>
	<thumbnail>https://image.tmdb.org/t/p/w1280/iRtJ7l2TRdcO0qf4rcSjpRogJ0j.jpg</thumbnail>
	<fanart>https://image.tmdb.org/t/p/w1280/7KEW0E9taysGjKBSwV6g0FeVdDJ.jpg</fanart>
</item>
<item>
	<title>[COLOR=white]Four Eyes[/COLOR]</title>
	<meta>
	<imdb>tt0071007</imdb>
	<content>episode</content>
	<tvshowtitle>Little House on the Prairie</tvshowtitle>
	<year>1975</year>
	<season>2</season>
	<episode>2</episode>
	</meta>
	<link>
	<sublink>search</sublink>
	<sublink>searchsd</sublink>
	</link>
	<thumbnail>https://image.tmdb.org/t/p/w1280/65dT62EXRLs5THvoGFd5oqLmMIM.jpg</thumbnail>
	<fanart>https://image.tmdb.org/t/p/w1280/7KEW0E9taysGjKBSwV6g0FeVdDJ.jpg</fanart>
</item>
<item>
	<title>[COLOR=white]Ebenezer Sprague[/COLOR]</title>
	<meta>
	<imdb>tt0071007</imdb>
	<content>episode</content>
	<tvshowtitle>Little House on the Prairie</tvshowtitle>
	<year>1975</year>
	<season>2</season>
	<episode>3</episode>
	</meta>
	<link>
	<sublink>search</sublink>
	<sublink>searchsd</sublink>
	</link>
	<thumbnail>https://image.tmdb.org/t/p/w1280/byjqcoy19innWmq7bZ2WSr40yfZ.jpg</thumbnail>
	<fanart>https://image.tmdb.org/t/p/w1280/7KEW0E9taysGjKBSwV6g0FeVdDJ.jpg</fanart>
</item>
<item>
	<title>[COLOR=white]In The Big Inning[/COLOR]</title>
	<meta>
	<imdb>tt0071007</imdb>
	<content>episode</content>
	<tvshowtitle>Little House on the Prairie</tvshowtitle>
	<year>1975</year>
	<season>2</season>
	<episode>4</episode>
	</meta>
	<link>
	<sublink>search</sublink>
	<sublink>searchsd</sublink>
	</link>
	<thumbnail>https://image.tmdb.org/t/p/w1280/tjddY2oG5Rx6Ci4E4FfJptVJiQT.jpg</thumbnail>
	<fanart>https://image.tmdb.org/t/p/w1280/7KEW0E9taysGjKBSwV6g0FeVdDJ.jpg</fanart>
</item>
<item>
	<title>[COLOR=white]Haunted House[/COLOR]</title>
	<meta>
	<imdb>tt0071007</imdb>
	<content>episode</content>
	<tvshowtitle>Little House on the Prairie</tvshowtitle>
	<year>1975</year>
	<season>2</season>
	<episode>5</episode>
	</meta>
	<link>
	<sublink>search</sublink>
	<sublink>searchsd</sublink>
	</link>
	<thumbnail>https://image.tmdb.org/t/p/w1280/7fIAY2ZCRe8vTYgFpj4nC5DrFGV.jpg</thumbnail>
	<fanart>https://image.tmdb.org/t/p/w1280/7KEW0E9taysGjKBSwV6g0FeVdDJ.jpg</fanart>
</item>
<item>
	<title>[COLOR=white]The Spring Dance[/COLOR]</title>
	<meta>
	<imdb>tt0071007</imdb>
	<content>episode</content>
	<tvshowtitle>Little House on the Prairie</tvshowtitle>
	<year>1975</year>
	<season>2</season>
	<episode>6</episode>
	</meta>
	<link>
	<sublink>search</sublink>
	<sublink>searchsd</sublink>
	</link>
	<thumbnail>https://image.tmdb.org/t/p/w1280/wJWv1rphULMqi6MB5zU3IijPuAd.jpg</thumbnail>
	<fanart>https://image.tmdb.org/t/p/w1280/7KEW0E9taysGjKBSwV6g0FeVdDJ.jpg</fanart>
</item>
<item>
	<title>[COLOR=white]Remember Me (1)[/COLOR]</title>
	<meta>
	<imdb>tt0071007</imdb>
	<content>episode</content>
	<tvshowtitle>Little House on the Prairie</tvshowtitle>
	<year>1975</year>
	<season>2</season>
	<episode>7</episode>
	</meta>
	<link>
	<sublink>search</sublink>
	<sublink>searchsd</sublink>
	</link>
	<thumbnail>https://image.tmdb.org/t/p/w1280/p3vawvU5k37lVesRuZMbl97hOS9.jpg</thumbnail>
	<fanart>https://image.tmdb.org/t/p/w1280/7KEW0E9taysGjKBSwV6g0FeVdDJ.jpg</fanart>
</item>
<item>
	<title>[COLOR=white]Remember Me (2)[/COLOR]</title>
	<meta>
	<imdb>tt0071007</imdb>
	<content>episode</content>
	<tvshowtitle>Little House on the Prairie</tvshowtitle>
	<year>1975</year>
	<season>2</season>
	<episode>8</episode>
	</meta>
	<link>
	<sublink>search</sublink>
	<sublink>searchsd</sublink>
	</link>
	<thumbnail>https://image.tmdb.org/t/p/w1280/8ebyx9ktgCy35T2aDGjvj7ftM7O.jpg</thumbnail>
	<fanart>https://image.tmdb.org/t/p/w1280/7KEW0E9taysGjKBSwV6g0FeVdDJ.jpg</fanart>
</item>
<item>
	<title>[COLOR=white]The Campout[/COLOR]</title>
	<meta>
	<imdb>tt0071007</imdb>
	<content>episode</content>
	<tvshowtitle>Little House on the Prairie</tvshowtitle>
	<year>1975</year>
	<season>2</season>
	<episode>9</episode>
	</meta>
	<link>
	<sublink>search</sublink>
	<sublink>searchsd</sublink>
	</link>
	<thumbnail>https://image.tmdb.org/t/p/w1280/rZkfNLJH1W4WrovJzaTl3D7XQDe.jpg</thumbnail>
	<fanart>https://image.tmdb.org/t/p/w1280/7KEW0E9taysGjKBSwV6g0FeVdDJ.jpg</fanart>
</item>
<item>
	<title>[COLOR=white]At The End Of The Rainbow[/COLOR]</title>
	<meta>
	<imdb>tt0071007</imdb>
	<content>episode</content>
	<tvshowtitle>Little House on the Prairie</tvshowtitle>
	<year>1975</year>
	<season>2</season>
	<episode>10</episode>
	</meta>
	<link>
	<sublink>search</sublink>
	<sublink>searchsd</sublink>
	</link>
	<thumbnail>https://image.tmdb.org/t/p/w1280/eWrhTrtnYndGrGMgNEwam5xUyjD.jpg</thumbnail>
	<fanart>https://image.tmdb.org/t/p/w1280/7KEW0E9taysGjKBSwV6g0FeVdDJ.jpg</fanart>
</item>
<item>
	<title>[COLOR=white]The Gift[/COLOR]</title>
	<meta>
	<imdb>tt0071007</imdb>
	<content>episode</content>
	<tvshowtitle>Little House on the Prairie</tvshowtitle>
	<year>1975</year>
	<season>2</season>
	<episode>11</episode>
	</meta>
	<link>
	<sublink>search</sublink>
	<sublink>searchsd</sublink>
	</link>
	<thumbnail>https://image.tmdb.org/t/p/w1280/us1BwPwSIEQcAU2v02wxIyZUXOl.jpg</thumbnail>
	<fanart>https://image.tmdb.org/t/p/w1280/7KEW0E9taysGjKBSwV6g0FeVdDJ.jpg</fanart>
</item>
<item>
	<title>[COLOR=white]His Father's Son[/COLOR]</title>
	<meta>
	<imdb>tt0071007</imdb>
	<content>episode</content>
	<tvshowtitle>Little House on the Prairie</tvshowtitle>
	<year>1976</year>
	<season>2</season>
	<episode>12</episode>
	</meta>
	<link>
	<sublink>search</sublink>
	<sublink>searchsd</sublink>
	</link>
	<thumbnail>https://image.tmdb.org/t/p/w1280/vsoFpnCpUcQo0P9ORQEdPy506Ni.jpg</thumbnail>
	<fanart>https://image.tmdb.org/t/p/w1280/7KEW0E9taysGjKBSwV6g0FeVdDJ.jpg</fanart>
</item>
<item>
	<title>[COLOR=white]The Talking Machine[/COLOR]</title>
	<meta>
	<imdb>tt0071007</imdb>
	<content>episode</content>
	<tvshowtitle>Little House on the Prairie</tvshowtitle>
	<year>1976</year>
	<season>2</season>
	<episode>13</episode>
	</meta>
	<link>
	<sublink>search</sublink>
	<sublink>searchsd</sublink>
	</link>
	<thumbnail>https://image.tmdb.org/t/p/w1280/pZpI2T2A6SbHQ1U6kwDCTjMZrAT.jpg</thumbnail>
	<fanart>https://image.tmdb.org/t/p/w1280/7KEW0E9taysGjKBSwV6g0FeVdDJ.jpg</fanart>
</item>
<item>
	<title>[COLOR=white]The Pride Of Walnut Grove[/COLOR]</title>
	<meta>
	<imdb>tt0071007</imdb>
	<content>episode</content>
	<tvshowtitle>Little House on the Prairie</tvshowtitle>
	<year>1976</year>
	<season>2</season>
	<episode>14</episode>
	</meta>
	<link>
	<sublink>search</sublink>
	<sublink>searchsd</sublink>
	</link>
	<thumbnail>https://image.tmdb.org/t/p/w1280/xurquFxjyyrMlQ1SjSiWi6nNQ9e.jpg</thumbnail>
	<fanart>https://image.tmdb.org/t/p/w1280/7KEW0E9taysGjKBSwV6g0FeVdDJ.jpg</fanart>
</item>
<item>
	<title>[COLOR=white]A Matter Of Faith[/COLOR]</title>
	<meta>
	<imdb>tt0071007</imdb>
	<content>episode</content>
	<tvshowtitle>Little House on the Prairie</tvshowtitle>
	<year>1976</year>
	<season>2</season>
	<episode>15</episode>
	</meta>
	<link>
	<sublink>search</sublink>
	<sublink>searchsd</sublink>
	</link>
	<thumbnail>https://image.tmdb.org/t/p/w1280/z3mvXMAM4xL74ByvCmOlE7cG4oo.jpg</thumbnail>
	<fanart>https://image.tmdb.org/t/p/w1280/7KEW0E9taysGjKBSwV6g0FeVdDJ.jpg</fanart>
</item>
<item>
	<title>[COLOR=white]The Runaway Caboose[/COLOR]</title>
	<meta>
	<imdb>tt0071007</imdb>
	<content>episode</content>
	<tvshowtitle>Little House on the Prairie</tvshowtitle>
	<year>1976</year>
	<season>2</season>
	<episode>16</episode>
	</meta>
	<link>
	<sublink>search</sublink>
	<sublink>searchsd</sublink>
	</link>
	<thumbnail>https://image.tmdb.org/t/p/w1280/otwhsFy2YGGX9v1lyiyDmSxwZZ1.jpg</thumbnail>
	<fanart>https://image.tmdb.org/t/p/w1280/7KEW0E9taysGjKBSwV6g0FeVdDJ.jpg</fanart>
</item>
<item>
	<title>[COLOR=white]Troublemaker[/COLOR]</title>
	<meta>
	<imdb>tt0071007</imdb>
	<content>episode</content>
	<tvshowtitle>Little House on the Prairie</tvshowtitle>
	<year>1976</year>
	<season>2</season>
	<episode>17</episode>
	</meta>
	<link>
	<sublink>search</sublink>
	<sublink>searchsd</sublink>
	</link>
	<thumbnail>https://image.tmdb.org/t/p/w1280/veyqHyTB8jJbVQZyqDE6WmSpA8y.jpg</thumbnail>
	<fanart>https://image.tmdb.org/t/p/w1280/7KEW0E9taysGjKBSwV6g0FeVdDJ.jpg</fanart>
</item>
<item>
	<title>[COLOR=white]The Long Road Home[/COLOR]</title>
	<meta>
	<imdb>tt0071007</imdb>
	<content>episode</content>
	<tvshowtitle>Little House on the Prairie</tvshowtitle>
	<year>1976</year>
	<season>2</season>
	<episode>18</episode>
	</meta>
	<link>
	<sublink>search</sublink>
	<sublink>searchsd</sublink>
	</link>
	<thumbnail>https://image.tmdb.org/t/p/w1280/8MgLyXZSnwJDPhLTM40ZeJqhkTl.jpg</thumbnail>
	<fanart>https://image.tmdb.org/t/p/w1280/7KEW0E9taysGjKBSwV6g0FeVdDJ.jpg</fanart>
</item>
<item>
	<title>[COLOR=white]For My Lady[/COLOR]</title>
	<meta>
	<imdb>tt0071007</imdb>
	<content>episode</content>
	<tvshowtitle>Little House on the Prairie</tvshowtitle>
	<year>1976</year>
	<season>2</season>
	<episode>19</episode>
	</meta>
	<link>
	<sublink>search</sublink>
	<sublink>searchsd</sublink>
	</link>
	<thumbnail>https://image.tmdb.org/t/p/w1280/ci18BtXjrvbgDY7AZsAezXtTV5z.jpg</thumbnail>
	<fanart>https://image.tmdb.org/t/p/w1280/7KEW0E9taysGjKBSwV6g0FeVdDJ.jpg</fanart>
</item>
<item>
	<title>[COLOR=white]Centennial[/COLOR]</title>
	<meta>
	<imdb>tt0071007</imdb>
	<content>episode</content>
	<tvshowtitle>Little House on the Prairie</tvshowtitle>
	<year>1976</year>
	<season>2</season>
	<episode>20</episode>
	</meta>
	<link>
	<sublink>search</sublink>
	<sublink>searchsd</sublink>
	</link>
	<thumbnail>https://image.tmdb.org/t/p/w1280/otFzngkC0UqofrWK2HBdNgyT0Lk.jpg</thumbnail>
	<fanart>https://image.tmdb.org/t/p/w1280/7KEW0E9taysGjKBSwV6g0FeVdDJ.jpg</fanart>
</item>
<item>
	<title>[COLOR=white]Soldier's Return[/COLOR]</title>
	<meta>
	<imdb>tt0071007</imdb>
	<content>episode</content>
	<tvshowtitle>Little House on the Prairie</tvshowtitle>
	<year>1976</year>
	<season>2</season>
	<episode>21</episode>
	</meta>
	<link>
	<sublink>search</sublink>
	<sublink>searchsd</sublink>
	</link>
	<thumbnail>https://image.tmdb.org/t/p/w1280/y9LNLAFOSCUB1A99fkk5Oetefdv.jpg</thumbnail>
	<fanart>https://image.tmdb.org/t/p/w1280/7KEW0E9taysGjKBSwV6g0FeVdDJ.jpg</fanart>
</item>
<item>
	<title>[COLOR=white]Going Home[/COLOR]</title>
	<meta>
	<imdb>tt0071007</imdb>
	<content>episode</content>
	<tvshowtitle>Little House on the Prairie</tvshowtitle>
	<year>1976</year>
	<season>2</season>
	<episode>22</episode>
	</meta>
	<link>
	<sublink>search</sublink>
	<sublink>searchsd</sublink>
	</link>
	<thumbnail>https://image.tmdb.org/t/p/w1280/bNg0hMVlDazQsgsdwXZGG6Ik0wg.jpg</thumbnail>
	<fanart>https://image.tmdb.org/t/p/w1280/7KEW0E9taysGjKBSwV6g0FeVdDJ.jpg</fanart>
</item>
