<item>
	<title>[COLOR=white]The Western Book of the Dead[/COLOR]</title>
	<meta>
	<imdb>tt2356777</imdb>
	<content>episode</content>
	<tvshowtitle>True Detective</tvshowtitle>
	<year>2015</year>
	<season>2</season>
	<episode>1</episode>
	</meta>
	<link>
	<sublink>search</sublink>
	<sublink>searchsd</sublink>
	</link>
	<thumbnail>https://image.tmdb.org/t/p/w1280/xU9WNshqgkYRxaMAoIYOvCU91pE.jpg</thumbnail>
	<fanart>https://image.tmdb.org/t/p/w1280/qDEIZWnyRxWTB9zCjyyj4mbURVp.jpg</fanart>
</item>
<item>
	<title>[COLOR=white]Night Finds You[/COLOR]</title>
	<meta>
	<imdb>tt2356777</imdb>
	<content>episode</content>
	<tvshowtitle>True Detective</tvshowtitle>
	<year>2015</year>
	<season>2</season>
	<episode>2</episode>
	</meta>
	<link>
	<sublink>search</sublink>
	<sublink>searchsd</sublink>
	</link>
	<thumbnail>https://image.tmdb.org/t/p/w1280/emZ2bLfqyJHWMqx97BitVPIQ2SL.jpg</thumbnail>
	<fanart>https://image.tmdb.org/t/p/w1280/qDEIZWnyRxWTB9zCjyyj4mbURVp.jpg</fanart>
</item>
<item>
	<title>[COLOR=white]Maybe Tomorrow[/COLOR]</title>
	<meta>
	<imdb>tt2356777</imdb>
	<content>episode</content>
	<tvshowtitle>True Detective</tvshowtitle>
	<year>2015</year>
	<season>2</season>
	<episode>3</episode>
	</meta>
	<link>
	<sublink>search</sublink>
	<sublink>searchsd</sublink>
	</link>
	<thumbnail>https://image.tmdb.org/t/p/w1280/hAWi1GEV10UXVTwKUG68983sAME.jpg</thumbnail>
	<fanart>https://image.tmdb.org/t/p/w1280/qDEIZWnyRxWTB9zCjyyj4mbURVp.jpg</fanart>
</item>
<item>
	<title>[COLOR=white]Down Will Come[/COLOR]</title>
	<meta>
	<imdb>tt2356777</imdb>
	<content>episode</content>
	<tvshowtitle>True Detective</tvshowtitle>
	<year>2015</year>
	<season>2</season>
	<episode>4</episode>
	</meta>
	<link>
	<sublink>search</sublink>
	<sublink>searchsd</sublink>
	</link>
	<thumbnail>https://image.tmdb.org/t/p/w1280/40croBi5GMTyJPDnTDLh8ENCh0r.jpg</thumbnail>
	<fanart>https://image.tmdb.org/t/p/w1280/qDEIZWnyRxWTB9zCjyyj4mbURVp.jpg</fanart>
</item>
<item>
	<title>[COLOR=white]Other Lives[/COLOR]</title>
	<meta>
	<imdb>tt2356777</imdb>
	<content>episode</content>
	<tvshowtitle>True Detective</tvshowtitle>
	<year>2015</year>
	<season>2</season>
	<episode>5</episode>
	</meta>
	<link>
	<sublink>search</sublink>
	<sublink>searchsd</sublink>
	</link>
	<thumbnail>https://image.tmdb.org/t/p/w1280/ecpJUMuukKU3Aamn8s9NkGzdNKq.jpg</thumbnail>
	<fanart>https://image.tmdb.org/t/p/w1280/qDEIZWnyRxWTB9zCjyyj4mbURVp.jpg</fanart>
</item>
<item>
	<title>[COLOR=white]Church in Ruins[/COLOR]</title>
	<meta>
	<imdb>tt2356777</imdb>
	<content>episode</content>
	<tvshowtitle>True Detective</tvshowtitle>
	<year>2015</year>
	<season>2</season>
	<episode>6</episode>
	</meta>
	<link>
	<sublink>search</sublink>
	<sublink>searchsd</sublink>
	</link>
	<thumbnail>https://image.tmdb.org/t/p/w1280/uxqRw7XU8cVDUhuO3AFntfq8g5W.jpg</thumbnail>
	<fanart>https://image.tmdb.org/t/p/w1280/qDEIZWnyRxWTB9zCjyyj4mbURVp.jpg</fanart>
</item>
<item>
	<title>[COLOR=white]Black Maps and Motel Rooms[/COLOR]</title>
	<meta>
	<imdb>tt2356777</imdb>
	<content>episode</content>
	<tvshowtitle>True Detective</tvshowtitle>
	<year>2015</year>
	<season>2</season>
	<episode>7</episode>
	</meta>
	<link>
	<sublink>search</sublink>
	<sublink>searchsd</sublink>
	</link>
	<thumbnail>https://image.tmdb.org/t/p/w1280/a50alacRPu7p8hcjrGk1kE6J3XK.jpg</thumbnail>
	<fanart>https://image.tmdb.org/t/p/w1280/qDEIZWnyRxWTB9zCjyyj4mbURVp.jpg</fanart>
</item>
<item>
	<title>[COLOR=white]Omega Station[/COLOR]</title>
	<meta>
	<imdb>tt2356777</imdb>
	<content>episode</content>
	<tvshowtitle>True Detective</tvshowtitle>
	<year>2015</year>
	<season>2</season>
	<episode>8</episode>
	</meta>
	<link>
	<sublink>search</sublink>
	<sublink>searchsd</sublink>
	</link>
	<thumbnail>https://image.tmdb.org/t/p/w1280/jrF8TX0ysB3UaGM2AOz76sUnEl6.jpg</thumbnail>
	<fanart>https://image.tmdb.org/t/p/w1280/qDEIZWnyRxWTB9zCjyyj4mbURVp.jpg</fanart>
</item>
